vasrch/__init__.py
vasrch/vasrch.py
vasrch-0.0.11.dist-info/LICENSE.txt
vasrch-0.0.11.dist-info/METADATA
vasrch-0.0.11.dist-info/WHEEL
vasrch-0.0.11.dist-info/top_level.txt
vasrch-0.0.11.dist-info/RECORD
