Metadata-Version: 2.1
Name: vasrch
Version: 0.0.11
Summary: Searching related data by image
Author: Steven Manangu (Varsitymart)
Author-email: <stevenmanangu360@gmail.com>
Keywords: python,image,search,image search,e-commerce,clustering,k-means
Classifier: Development Status :: 1 - Planning
Classifier: Intended Audience :: Developers
Classifier: Programming Language :: Python :: 3
Classifier: Operating System :: Unix
Classifier: Operating System :: MacOS :: MacOS X
Classifier: Operating System :: Microsoft :: Windows
License-File: LICENSE.txt
Requires-Dist: numpy
Requires-Dist: pandas
Requires-Dist: matplotlib
Requires-Dist: scikit-learn
Requires-Dist: tensorflow
Requires-Dist: joblib
Requires-Dist: cloudinary
Requires-Dist: requests
